igrf_model/__init__.py
igrf_model/_igrf13syn.py
igrf_model/model.py
igrf_model/types.py
igrf_model/utils.py
igrf_model/vector.py
igrf_model/version.py
igrf_model/data/__init__.py
igrf_model/data/igrf13.txt
igrf_model-1.1.4.dist-info/METADATA
igrf_model-1.1.4.dist-info/WHEEL
igrf_model-1.1.4.dist-info/licenses/LICENSE.md
igrf_model-1.1.4.dist-info/RECORD
